./.gitignore
./PKG-INFO
./README.md
./pyproject.toml
./vision_agents/plugins/deepgram/__init__.py
./vision_agents/plugins/deepgram/deepgram_stt.py
./vision_agents/plugins/deepgram/tts.py
vision_agents/plugins/deepgram/__init__.py
vision_agents/plugins/deepgram/deepgram_stt.py
vision_agents/plugins/deepgram/tts.py
vision_agents_plugins_deepgram-0.2.10.dist-info/METADATA
vision_agents_plugins_deepgram-0.2.10.dist-info/WHEEL
vision_agents_plugins_deepgram-0.2.10.dist-info/RECORD
