Metadata-Version: 2.4
Name: vision-agents-plugins-deepgram
Version: 0.2.10
Summary: Deepgram STT and TTS integration for Vision Agents
Project-URL: Documentation, https://visionagents.ai/
Project-URL: Website, https://visionagents.ai/
Project-URL: Source, https://github.com/GetStream/Vision-Agents
License-Expression: MIT
Keywords: AI,STT,TTS,agents,deepgram,speech-to-text,text-to-speech,transcription,voice agents
Requires-Python: >=3.10
Requires-Dist: deepgram-sdk!=5.3.1,<6,>=5
Requires-Dist: numpy<2.3,>=2.2.6
Requires-Dist: vision-agents
